taurex_multimodel/__init__.py
taurex_multimodel/model/__init__.py
taurex_multimodel/model/adaptive_model.py
taurex_multimodel/model/multichemistry.py
taurex_multimodel/model/multidirect.py
taurex_multimodel/model/multieclipse.py
taurex_multimodel/model/multitransit.py
taurex_multimodel/model/parametermodel.py
taurex_multimodel-1.0.0.dist-info/licenses/LICENSE
taurex_multimodel-1.0.0.dist-info/METADATA
taurex_multimodel-1.0.0.dist-info/WHEEL
taurex_multimodel-1.0.0.dist-info/entry_points.txt
taurex_multimodel-1.0.0.dist-info/top_level.txt
taurex_multimodel-1.0.0.dist-info/RECORD
