Metadata-Version: 2.4
Name: taurex_multimodel
Version: 1.0.0
Summary: Plugin to compute models with multiple regions
Home-page: https://github.com/groningen-exoatmospheres/taurex-multimodel
Author: Quentin Changeat
Author-email: 
License: BSD
Provides: taurex_multimodel
License-File: LICENSE
Requires-Dist: taurex
Dynamic: author
Dynamic: home-page
Dynamic: license
Dynamic: license-file
Dynamic: provides
Dynamic: requires-dist
Dynamic: summary
